fileloader/__init__.py
fileloader/helpers.py
fileloader/loaders.py
fileloader/py.typed
fileloader/streamers.py
fileloader/writers.py
pyfileloader-0.0.14.dist-info/METADATA
pyfileloader-0.0.14.dist-info/WHEEL
pyfileloader-0.0.14.dist-info/top_level.txt
pyfileloader-0.0.14.dist-info/RECORD
