Metadata-Version: 2.4
Name: pyfileloader
Version: 0.0.14
Summary: Load common JSON formats quickly, CSV too. Supports writing as well.
Author: Scott Walsh
Author-email: scott@invisiblethreat.ca
Maintainer: Scott Walsh
Maintainer-email: scott@invisiblethreat.ca
Project-URL: homepage, https://github.com/invisiblethreat/pyfileloader
Project-URL: documentation, https://github.com/invisiblethreat/pyfileloader/blob/main/README.md
Project-URL: repository, https://github.com/invisiblethreat/pyfileloader
Keywords: json,jsonl,ndjson,gzip,fileloader
Classifier: Development Status :: 4 - Beta
Classifier: Programming Language :: Python
Requires-Python: >=3.7
